{
  "speisen": [
    {
      "Kategorie": "Vorspeisen",
      "Name": "Spargelcremesuppe",
      "Beschreibung": " ",
      "Menge": " ",
      "Preis": " ",
      "": ""
    },
    {
      "Kategorie": "Hauptgerichte",
      "Name": "Maispoularde mit neuen Kartoffeln, gegrilltem grünem Spargel und Sauce Choron",
      "Beschreibung": " ",
      "Menge": " ",
      "Preis": " ",
      "": ""
    },
    {
      "Kategorie": "Hauptgerichte",
      "Name": "Linguine mit Knoblauchgarnelen",
      "Beschreibung": " ",
      "Menge": " ",
      "Preis": " ",
      "": ""
    },
    {
      "Kategorie": "Hauptgerichte",
      "Name": "Linguine mit gegrilltem grünem Spargel",
      "Beschreibung": " ",
      "Menge": " ",
      "Preis": " ",
      "": ""
    },
    {
      "Kategorie": "",
      "Name": "",
      "Beschreibung": "",
      "Menge": "",
      "Preis": "",
      "": ""
    },
    {
      "Kategorie": "",
      "Name": "",
      "Beschreibung": "",
      "Menge": "",
      "Preis": "",
      "": ""
    },
    {
      "Kategorie": "",
      "Name": "",
      "Beschreibung": "",
      "Menge": "",
      "Preis": "",
      "": ""
    },
    {
      "Kategorie": "",
      "Name": "",
      "Beschreibung": "",
      "Menge": "",
      "Preis": "",
      "": ""
    },
    {
      "Kategorie": "",
      "Name": "",
      "Beschreibung": "",
      "Menge": "",
      "Preis": "",
      "": ""
    },
    {
      "Kategorie": "",
      "Name": "",
      "Beschreibung": "",
      "Menge": "",
      "Preis": "",
      "": ""
    },
    {
      "Kategorie": "",
      "Name": "",
      "Beschreibung": "",
      "Menge": "",
      "Preis": "",
      "": ""
    },
    {
      "Kategorie": "",
      "Name": "",
      "Beschreibung": "",
      "Menge": "",
      "Preis": "",
      "": ""
    },
    {
      "Kategorie": "",
      "Name": "",
      "Beschreibung": "",
      "Menge": "",
      "Preis": "",
      "": ""
    },
    {
      "Kategorie": "",
      "Name": "",
      "Beschreibung": "",
      "Menge": "",
      "Preis": "",
      "": ""
    },
    {
      "Kategorie": "",
      "Name": "",
      "Beschreibung": "",
      "Menge": "",
      "Preis": "",
      "": ""
    },
    {
      "Kategorie": "",
      "Name": "",
      "Beschreibung": "",
      "Menge": "",
      "Preis": "",
      "": ""
    },
    {
      "Kategorie": "",
      "Name": "",
      "Beschreibung": "",
      "Menge": "",
      "Preis": "",
      "": " "
    }
  ]
}